prettypy/__init__.py
prettypy/composer.py
prettypy/layout.py
prettypy/pretty.py
prettypy/pretty_template.py
prettypy/style.py
prettypy-0.2.1.dist-info/LICENSE
prettypy-0.2.1.dist-info/METADATA
prettypy-0.2.1.dist-info/WHEEL
prettypy-0.2.1.dist-info/top_level.txt
prettypy-0.2.1.dist-info/RECORD
