Metadata-Version: 2.1
Name: prettypy
Version: 0.2.1
Summary: A Python library to create pretty terminal output
Home-page: https://github.com/uss-zerodata/prettypy
Author: zerodata
Author-email: zerodata@amissum.de
Project-URL: Docs, https://github.com/uss-zerodata/prettypy
Classifier: Programming Language :: Python :: 3
Classifier: License :: OSI Approved :: MIT License
Classifier: Operating System :: OS Independent
Requires-Python: >=3.8
License-File: LICENSE
